topic_modelling_tools_fast-0.7.dev0.dist-info/DESCRIPTION.rst
topic_modelling_tools_fast-0.7.dev0.dist-info/METADATA
topic_modelling_tools_fast-0.7.dev0.dist-info/RECORD
topic_modelling_tools_fast-0.7.dev0.dist-info/WHEEL
topic_modelling_tools_fast-0.7.dev0.dist-info/metadata.json
topic_modelling_tools_fast-0.7.dev0.dist-info/top_level.txt
topicmodel_tests/__init__.py
topicmodel_tests/testsuite.py
topicmodels/__init__.py
topicmodels/bow.py
topicmodels/bow_data.py
topicmodels/dict_neg_mp.txt
topicmodels/dict_pos_mp.txt
topicmodels/dict_uncertainty.txt
topicmodels/preprocess.py
topicmodels/preprocess_data.py
topicmodels/stopwords_long.txt
topicmodels/stopwords_short.txt
topicmodels/LDA/__init__.py
topicmodels/LDA/gibbs.py
topicmodels/multimix/__init__.py
topicmodels/multimix/inference.py
topicmodels/samplers/__init__.py
topicmodels/samplers/samplers_lda.cpython-36m-darwin.so
