Metadata-Version: 2.0
Name: topic-modelling-tools-fast
Version: 0.7.dev0
Summary: Python library that performs Latent Dirichlet Allocation using Gibbs sampling.
Home-page: https://github.com/alan-turing-institute/topic-modelling-tools/tree/with_gsl
Author: Stephen Hansen
Author-email: stephen.hansen@economics.ox.ac.uk
License: LICENSE
Platform: UNKNOWN
Requires-Dist: Cython (>=0.20.1)
Requires-Dist: nltk (>=3.2.4)
Requires-Dist: numpy (>=1.13.3)
Requires-Dist: pandas (>=0.20.3)
Requires-Dist: scipy (>=0.19.1)
